qint/__init__.py
qint/exceptions.py
qint/qint.py
qint/utils.py
tests/__init__.py
tests/test_qint.py
tests/test_utils.py
qint-0.2.0.dist-info/LICENSE
qint-0.2.0.dist-info/METADATA
qint-0.2.0.dist-info/WHEEL
qint-0.2.0.dist-info/top_level.txt
qint-0.2.0.dist-info/RECORD
