Metadata-Version: 2.1
Name: qint
Version: 0.2.0
Summary: Quantized Integer type in Python!
Author: Neural Dynamics
Author-email: support@neuraldynamicsai.com
License: MIT
Project-URL: GitHub, https://github.com/neuraldynamicsai/qint
License-File: LICENSE
